zc/form/TODO.rst
zc/form/__init__.py
zc/form/configure.zcml
zc/form/field.py
zc/form/i18n.py
zc/form/interfaces.py
zc/form/source.py
zc/form/tests.py
zc/form/browser/__init__.py
zc/form/browser/combinationwidget.pt
zc/form/browser/combinationwidget.py
zc/form/browser/combinationwidget.rst
zc/form/browser/configure.zcml
zc/form/browser/display.pt
zc/form/browser/dummy_macros.pt
zc/form/browser/exceptionviews.py
zc/form/browser/form.pt
zc/form/browser/ftesting.zcml
zc/form/browser/interfaces.py
zc/form/browser/mruwidget.py
zc/form/browser/mruwidget.rst
zc/form/browser/overrides.zcml
zc/form/browser/testing.py
zc/form/browser/timezone_queryview.pt
zc/form/browser/tzwidget.py
zc/form/browser/unionwidget.pt
zc/form/browser/unionwidget.py
zc/form/browser/widgetapi.py
zc/form/browser/mruwidget_resources/mruwidget.js
zc/form/browser/tests/__init__.py
zc/form/browser/tests/test_functional.py
zc/form/browser/tests/test_unittest.py
zc_form-3.0.dist-info/licenses/LICENSE.txt
zc_form-3.0.dist-info/METADATA
zc_form-3.0.dist-info/WHEEL
zc_form-3.0.dist-info/top_level.txt
zc_form-3.0.dist-info/RECORD
