Metadata-Version: 2.4
Name: zc.form
Version: 3.0
Summary: Extra browser widgets and alternative approaches for zope.formlib.
Home-page: https://github.com/zopefoundation/zc.form
Author: Zope Foundation and Contributors
Author-email: zope-dev@zope.dev
License: ZPL-2.1
Keywords: zope formlib form widget extra
Classifier: Environment :: Web Environment
Classifier: Intended Audience :: Developers
Classifier: License :: OSI Approved :: Zope Public License
Classifier: Programming Language :: Python :: 3
Classifier: Programming Language :: Python :: 3.9
Classifier: Programming Language :: Python :: 3.10
Classifier: Programming Language :: Python :: 3.11
Classifier: Programming Language :: Python :: 3.12
Classifier: Programming Language :: Python :: 3.13
Classifier: Programming Language :: Python :: Implementation :: CPython
Classifier: Programming Language :: Python :: Implementation :: PyPy
Classifier: Natural Language :: English
Classifier: Operating System :: OS Independent
Classifier: Topic :: Internet :: WWW/HTTP
Classifier: Framework :: Zope :: 3
Requires-Python: >=3.9
License-File: LICENSE.txt
Requires-Dist: pytz
Requires-Dist: setuptools
Requires-Dist: zc.sourcefactory
Requires-Dist: zope.browserpage
Requires-Dist: zope.cachedescriptors
Requires-Dist: zope.catalog
Requires-Dist: zope.component>=3.8
Requires-Dist: zope.exceptions
Requires-Dist: zope.formlib>=4.0
Requires-Dist: zope.index
Requires-Dist: zope.interface
Requires-Dist: zope.publisher
Requires-Dist: zope.schema>=3.6
Requires-Dist: zope.security
Provides-Extra: mruwidget
Requires-Dist: zope.annotation; extra == "mruwidget"
Requires-Dist: BTrees; extra == "mruwidget"
Requires-Dist: persistent; extra == "mruwidget"
Requires-Dist: zc.resourcelibrary; extra == "mruwidget"
Provides-Extra: test
Requires-Dist: zope.annotation; extra == "test"
Requires-Dist: BTrees; extra == "test"
Requires-Dist: persistent; extra == "test"
Requires-Dist: zc.resourcelibrary; extra == "test"
Requires-Dist: zope.app.appsetup; extra == "test"
Requires-Dist: zope.app.principalannotation; extra == "test"
Requires-Dist: zope.app.wsgi[testlayer]>=5.2; extra == "test"
Requires-Dist: zope.configuration; extra == "test"
Requires-Dist: zope.container; extra == "test"
Requires-Dist: zope.testing; extra == "test"
Requires-Dist: zope.testrunner>=6.4; extra == "test"
Requires-Dist: zope.traversing; extra == "test"
Provides-Extra: slimtest
Requires-Dist: zope.app.appsetup; extra == "slimtest"
Requires-Dist: zope.app.principalannotation; extra == "slimtest"
Requires-Dist: zope.app.wsgi[testlayer]>=5.2; extra == "slimtest"
Requires-Dist: zope.configuration; extra == "slimtest"
Requires-Dist: zope.container; extra == "slimtest"
Requires-Dist: zope.testing; extra == "slimtest"
Requires-Dist: zope.testrunner>=6.4; extra == "slimtest"
Requires-Dist: zope.traversing; extra == "slimtest"
Dynamic: author
Dynamic: author-email
Dynamic: classifier
Dynamic: description
Dynamic: home-page
Dynamic: keywords
Dynamic: license
Dynamic: license-file
Dynamic: provides-extra
Dynamic: requires-dist
Dynamic: requires-python
Dynamic: summary
